memory_mcp_server/__init__.py
memory_mcp_server/exceptions.py
memory_mcp_server/interfaces.py
memory_mcp_server/knowledge_graph_manager.py
memory_mcp_server/main.py
memory_mcp_server/backends/__init__.py
memory_mcp_server/backends/base.py
memory_mcp_server/backends/jsonl.py
memory_mcp_server-0.2.0.dist-info/METADATA
memory_mcp_server-0.2.0.dist-info/WHEEL
memory_mcp_server-0.2.0.dist-info/licenses/LICENSE
memory_mcp_server-0.2.0.dist-info/RECORD
