Metadata-Version: 2.4
Name: memory-mcp-server
Version: 0.2.0
Summary: MCP server for managing Claude's memory and knowledge graph
License-File: LICENSE
Requires-Python: >=3.12
Requires-Dist: aiofiles
Requires-Dist: mcp-sdk
Provides-Extra: test
Requires-Dist: pytest; extra == 'test'
Requires-Dist: pytest-asyncio; extra == 'test'
Requires-Dist: pytest-cov; extra == 'test'
